typediter/__init__.py
typediter/_helpers.py
typediter/exceptions.py
typediter/py.typed
typediter/types.py
typediter/utils.py
typediter/classes/__init__.py
typediter/classes/_base.py
typediter/classes/complete/__init__.py
typediter/classes/complete/frozenset.py
typediter/classes/complete/list.py
typediter/classes/complete/set.py
typediter/classes/complete/tuple.py
typediter/classes/light/__init__.py
typediter/classes/light/frozenset.py
typediter/classes/light/list.py
typediter/classes/light/set.py
typediter/classes/light/tuple.py
typediter-1.0.0.dist-info/LICENSE
typediter-1.0.0.dist-info/METADATA
typediter-1.0.0.dist-info/WHEEL
typediter-1.0.0.dist-info/top_level.txt
typediter-1.0.0.dist-info/RECORD
