Metadata-Version: 2.1
Name: typediter
Version: 1.0.0
Summary: Type-safe versions of Python's builtin iterables
Author-email: Didier Martin <didier.martin.dev@gmail.com>
License: MIT License
Project-URL: Homepage, https://github.com/Nebulaevo/typediter
Project-URL: Issues, https://github.com/Nebulaevo/typediter/issues
Project-URL: Changelog, https://github.com/Nebulaevo/typediter/blob/main/CHANGELOG.md
Keywords: type safe,type-safe,type-hints,type-checking,typed,iterable,iterables,list,tuple,set,frozenset
Classifier: Operating System :: OS Independent
Classifier: License :: OSI Approved :: MIT License
Classifier: Intended Audience :: Developers
Classifier: Typing :: Typed
Classifier: Programming Language :: Python
Classifier: Programming Language :: Python :: 3
Classifier: Programming Language :: Python :: 3 :: Only
Classifier: Programming Language :: Python :: 3.11
Classifier: Programming Language :: Python :: 3.12
Requires-Python: >=3.11
License-File: LICENSE
